autoomics/__init__.py
autoomics/cli.py
autoomics/config.py
autoomics/main.py
autoomics/runner.py
autoomics/modules/__init__.py
autoomics/modules/detect_data.py
autoomics/modules/detect_specifies.py
autoomics/modules/download_reference.py
autoomics/modules/explain_result.py
autoomics/modules/pipeline_launcher.py
autoomics/modules/report_generator.py
autoomics/modules/utils.py
autoomics-0.1.9.dist-info/licenses/LICENSE
autoomics-0.1.9.dist-info/METADATA
autoomics-0.1.9.dist-info/WHEEL
autoomics-0.1.9.dist-info/entry_points.txt
autoomics-0.1.9.dist-info/top_level.txt
autoomics-0.1.9.dist-info/RECORD
