Metadata-Version: 2.4
Name: autoomics
Version: 0.1.9
Summary: Un outil pour faire du multi-omique analyse (bulk seq, rnaseq, chip seq, atac seq)
Home-page: https://github.com/TonNom/mon_package
Author: Jordan BABADOUDOU
Author-email: jordan.babadoudou@umontreal.ca
Classifier: Programming Language :: Python :: 3
Classifier: License :: OSI Approved :: MIT License
Classifier: Operating System :: OS Independent
License-File: LICENSE
Requires-Dist: pandas
Requires-Dist: rich
Requires-Dist: biopython
Requires-Dist: openai
Requires-Dist: jinja2
Requires-Dist: setuptools
Dynamic: author
Dynamic: author-email
Dynamic: classifier
Dynamic: description-content-type
Dynamic: home-page
Dynamic: license-file
Dynamic: requires-dist
Dynamic: summary
